chess_scanparsers/__init__.py
chess_scanparsers/scanparsers.py
chess_scanparsers-2026.1.23.dist-info/METADATA
chess_scanparsers-2026.1.23.dist-info/WHEEL
chess_scanparsers-2026.1.23.dist-info/top_level.txt
chess_scanparsers-2026.1.23.dist-info/RECORD
