Metadata-Version: 2.1
Name: chess_scanparsers
Version: 2026.1.23
Summary: Utilities for parsing data and metadata for CHESS scans.
Home-page: https://github.com/CHESSComputing/chess-scanparsers
Author: Keara Soloway, Rolf Verberg
Author-email: 
Classifier: Programming Language :: Python :: 3
Classifier: License :: OSI Approved :: MIT License
Classifier: Operating System :: OS Independent
Requires-Python: >=3.8
Requires-Dist: certif-pyspec
